irv_autopkg_client/__init__.py
irv_autopkg_client/client.py
irv_autopkg_client/tests/__init__.py
irv_autopkg_client/tests/test_boundary
irv_autopkg_client/tests/test_boundary_geometry
irv_autopkg_client/tests/test_boundary_list
irv_autopkg_client/tests/test_boundary_search_by_coordinates
irv_autopkg_client/tests/test_boundary_search_by_name
irv_autopkg_client/tests/test_client.py
irv_autopkg_client/tests/test_dataset
irv_autopkg_client/tests/test_dataset_list
irv_autopkg_client/tests/test_extract
irv_autopkg_client/tests/test_extract_list
irv_autopkg_client/tests/test_server_liveness
irv_autopkg_client/tests/test_server_readiness
irv_autopkg_client-0.4.0.dist-info/LICENSE
irv_autopkg_client-0.4.0.dist-info/METADATA
irv_autopkg_client-0.4.0.dist-info/WHEEL
irv_autopkg_client-0.4.0.dist-info/RECORD
