Metadata-Version: 2.3
Name: irv-autopkg-client
Version: 0.4.0
Summary: A client for accessing the infra-risk-vis autopackage API
License: MIT
Keywords: climate,infrastructure,hazard,risk,data,extract
Author: Fred Thomas
Author-email: fred.thomas@eci.ox.ac.uk
Requires-Python: >=3.9,<4.0
Classifier: License :: OSI Approved :: MIT License
Classifier: Programming Language :: Python :: 3
Classifier: Programming Language :: Python :: 3.9
Classifier: Programming Language :: Python :: 3.10
Classifier: Programming Language :: Python :: 3.11
Classifier: Programming Language :: Python :: 3.12
Classifier: Programming Language :: Python :: 3.13
Requires-Dist: requests (>=2.28,<3.0)
